{
  "title": "Junior IT-Risiko- Manager (m/w/d)",
  "location": "Linz, OÖ",
  "contract_type": null,
  "body": "<div></div><p></p><div><div><div><div><div><div><div><div><div>Unser gemeinsames Ziel: </div><div>Wir verstärken unser Team am Standort Linz und suchen Unterstützung im Bereich\n<br>\nIT-Risikomanagement.\n</div></div><br>\n<div><div>Ihre wichtigsten Aufgaben:\n</div><div><ul><li>Du führst Schutzbedarfs- und Risikoanalysen durch (CRISAM® Methode).\n</li><li>Du erstellst und entwickelst selbständig Risikoberichte für das Management.\n</li><li>Du erarbeitest und entwickelst Prozesse im Bereich Information Risk Management.\n</li><li>Du analysierst den Risikoappetit der Geschäftsprozesse in der 3 Banken Gruppe.\n</li><li>Du dokumentierst die Abhängigkeiten risikorelevanter IT-Services.\n</li><li>Du unterstützt die Banken im operativen Risikomanagement.\n</li><li>Du dokumentierst und koordinierst die Umsetzung von Maßnahmen.\n</li><li>Du unterstützt die Vorbereitung zur Zertifizierung nach ISO 27001.\n</li></ul></div></div><br>\n<div><div>Ihr Profil:\n</div><div><ul><li>IT-Ausbildung mit Schwerpunkt „IT-Risiko Management“ bzw. „IT-Security“\n</li><li>Einschlägige Berufserfahrung vorteilhaft (Bank, operationelles Risikomanagement)\n</li><li>Kenntnis einschlägiger IT-Sicherheits-Standards/Normen (ISO 27000, ISO 31000, Cobit, BSI Grundschutz)\n</li><li>Genauigkeit und Qualitätsbewusstsein\n</li><li>Eigeninitiative und Flexibilität\n</li><li>Gutes Auftreten, Kundenorientierung, Lernbereitschaft sowie Beratermentalität\n</li><li>Teamfähigkeit\n</li><li>Reisebereitschaft\n</li><li>ausgeprägte Kommunikationsfähigkeit und lösungsorientiertes Denken\n</li><li>gute Englisch-Kenntnisse in Wort und Schrift\n</li></ul></div></div><br>\n<div><div>Gehaltsangabe: </div><div>Wir bieten ein sehr interessantes und entwicklungsfähiges Aufgabengebiet.\n<br>\nDas kollektivvertragliche Mindestgehalt (IT-KV) beträgt monatlich EUR 2.518,- brutto. Die tatsächliche Bezahlung hängt von deiner Ausbildung und Berufserfahrung ab.</div></div></div></div></div></div></div></div></div><p></p><div></div>",
  "url": "https://at.indeed.com/rc/clk?jk=3c7e9bc0963b224d&fccid=77c9fb3001c9e5ff&vjs=3",
  "date": "2020-05-12"
}