{
  "Veröffentlicht:": "Vor 6 Tagen",
  "Branchen": "Unternehmensberatung",
  "": "",
  "location": "Wien, W 1010",
  "contract_type": "Teilzeit, Festanstellung",
  "title": "Naturwissenschaftler/in / Techniker/in Energiewirtschaft (Jahresgehalt ab € 60.000) - Wagner, Elbling & Company",
  "subtitle": "Wien, W 1010",
  "body": "<i_jt_headsection></i_jt_headsection>\n\n\n  <script src=\"https://code.jquery.com/jquery-3.3.1.min.js\"></script>\n  <script type=\"text/javascript\" src=\"https://coda.newjobs.com/Assets/MUX/JaJobViewCloud/2020.05.0.760/js/app.js30.iframe.bundle.js\"></script>\n  <i_jt_header visible=\"True\"></i_jt_header><div id=\"job_summary\" style=\"display:none\"></div>\n<span id=\"TrackingJobBody\" name=\"TrackingJobBody\">\n<center>\n  <table class=\"ia-wrap\" width=\"600\" cellspacing=\"0\" cellpadding=\"0\" border=\"0\">\n    <tbody>\n      <tr>\n        <td colspan=\"2\" valign=\"top\"><table width=\"530\" cellspacing=\"0\" cellpadding=\"0\" border=\"0\">\n            <tbody>\n              <tr>\n                <td width=\"28\"><img src=\"https://media.newjobs.com/ftpinta/xjp97297atx/xjp97297atx_e001.gif\" alt=\"\" width=\"28\" height=\"1\" border=\"0\"></td>\n                <td width=\"210\"><img src=\"https://media.newjobs.com/ftpinta/xjp97297atx/xjp97297atx_e001.gif\" alt=\"\" width=\"210\" height=\"1\" border=\"0\"></td>\n                <td width=\"292\"><img src=\"https://media.newjobs.com/ftpinta/xjp97297atx/xjp97297atx_e001.gif\" alt=\"\" width=\"292\" height=\"1\" border=\"0\"></td>\n              </tr>\n              <tr>\n                <td width=\"28\"><img src=\"https://media.newjobs.com/ftpinta/xjp97297atx/xjp97297atx_e001.gif\" alt=\"\" width=\"28\" height=\"1\" border=\"0\"></td>\n                <td width=\"200\" valign=\"bottom\"><div class=\"kopf\">Internationale Unternehmensberatung für Energiewirtschaft mit Sitz in Wien\nsucht:\n\n  </div></td>\n                <td width=\"292\"><a data-role=\"none\" href=\"http://www.wecom.at\" target=\"_blank\"><img src=\"https://media.newjobs.com/ftpinta/xjp66326atx/xjp66326atx_e001.gif\" alt=\"\" width=\"292\" height=\"105\" border=\"0\"></a></td>\n              </tr>\n            </tbody>\n          </table></td>\n        <td valign=\"top\" background=\"https://media.newjobs.com/ftpinta/xjp66326atx/xjp66326atx_e002.gif\"><img alt=\"\" src=\"https://media.newjobs.com/ftpinta/xjp66326atx/xjp66326atx_e003.gif\" class=\"noprint\" width=\"64\" height=\"80\"></td>\n      </tr>\n      <tr>\n        <td background=\"https://media.newjobs.com/ftpinta/xjp66326atx/xjp66326atx_e004.gif\"><img alt=\"\" src=\"https://media.newjobs.com/ftpinta/xjp66326atx/xjp66326atx_e004.gif\" class=\"noprint\" width=\"65\" height=\"1\"></td>\n        <td background=\"https://media.newjobs.com/ftpinta/xjp66326atx/xjp66326atx_e005.gif\"><div class=\"titel\"> </div>\n          <img alt=\"\" src=\"https://media.newjobs.com/ftpinta/xjp66326atx/xjp66326atx_e005.gif\" width=\"471\" height=\"1\"></td>\n        <td background=\"https://media.newjobs.com/ftpinta/xjp66326atx/xjp66326atx_e002.gif\"><img alt=\"\" src=\"https://media.newjobs.com/ftpinta/xjp66326atx/xjp66326atx_e002.gif\" width=\"64\" height=\"1\"></td>\n      </tr>\n      <tr>\n        <td><img alt=\"\" src=\"https://media.newjobs.com/ftpinta/xjp66326atx/xjp66326atx_e006.gif\" class=\"noprint\" width=\"65\" height=\"20\"></td>\n        <td><img alt=\"\" src=\"https://media.newjobs.com/ftpinta/xjp66326atx/xjp66326atx_e007.gif\" class=\"noprint\" width=\"471\" height=\"20\"></td>\n        <td><img alt=\"\" src=\"https://media.newjobs.com/ftpinta/xjp66326atx/xjp66326atx_e008.gif\" class=\"noprint\" width=\"64\" height=\"20\"></td>\n      </tr>\n      <tr>\n        <td background=\"https://media.newjobs.com/ftpinta/xjp66326atx/xjp66326atx_e004.gif\"><img alt=\"\" src=\"https://media.newjobs.com/ftpinta/xjp66326atx/xjp66326atx_e004.gif\" class=\"noprint\" width=\"65\" height=\"1\"></td>\n        <td background=\"https://media.newjobs.com/ftpinta/xjp66326atx/xjp66326atx_e005.gif\"><div class=\"text\"><br>\n          </div>\n\t\t\t \n\t\t\t\n          <div id=\"titlebox\">\n\t\t\t \n\n\n            <h1>Naturwissenschaftler/in / Techniker/in <br> für die\n\t\t\t\tEnergiewirtschaft (Jahresgehalt ab € 60.000)\n\n</h1>\n          <!--  <h2> (Jahresgehalt ab € 55.000)</h2>-->\n          </div>\n          <img alt=\"\" src=\"https://media.newjobs.com/ftpinta/xjp66326atx/xjp66326atx_e005.gif\" width=\"471\" height=\"1\"></td>\n        <td background=\"https://media.newjobs.com/ftpinta/xjp66326atx/xjp66326atx_e002.gif\"><img alt=\"\" src=\"https://media.newjobs.com/ftpinta/xjp66326atx/xjp66326atx_e002.gif\" class=\"noprint\" width=\"64\" height=\"1\"></td>\n      </tr>\n      <tr>\n        <td><img alt=\"\" src=\"https://media.newjobs.com/ftpinta/xjp66326atx/xjp66326atx_e006.gif\" class=\"noprint\" width=\"65\" height=\"20\"></td>\n        <td><img alt=\"\" src=\"https://media.newjobs.com/ftpinta/xjp66326atx/xjp66326atx_e007.gif\" class=\"noprint\" width=\"471\" height=\"20\"></td>\n        <td><img alt=\"\" src=\"https://media.newjobs.com/ftpinta/xjp66326atx/xjp66326atx_e008.gif\" class=\"noprint\" width=\"64\" height=\"20\"></td>\n      </tr>\n      <tr>\n        <td background=\"https://media.newjobs.com/ftpinta/xjp66326atx/xjp66326atx_e004.gif\"><img alt=\"\" src=\"https://media.newjobs.com/ftpinta/xjp66326atx/xjp66326atx_e004.gif\" class=\"noprint\" width=\"65\" height=\"1\"></td>\n        <td background=\"https://media.newjobs.com/ftpinta/xjp66326atx/xjp66326atx_e005.gif\"><br>\n          <div class=\"text\">\n            <p>\n\t\t\t\tDie Versorgung Europas mit <strong>Gas und Strom</strong> erlebt den größten <strong>Umbau</strong> ihrer Ge­schichte. Die\n\t\t\t\t<strong>Dekarbonisierung (Klimaschutz), Dezentralisierung und Digi­ta­lisie­rung der Energiewirtschaft</strong>\n\t\t\t\tstellen etablierte Geschäftsmodelle vor große Her­aus­for­de­run­gen. <strong>Erneuerbare Energien</strong> werden\n\t\t\t\timmer wichtiger. <strong>Die wirtschaftlichen Grund­la­gen der Energieversorgung werden neu definiert</strong>.\n\t\t\t\tEnergie wird zunehmend auf börsenähnlichen Märkten gehandelt – <strong>Energiemärkte und\n\t\t\t\tFinanzmärkte rücken zusammen</strong>. Versorgungssicherheit muss neu geregelt werden, sowohl\n\t\t\t\ttechnisch als auch geopolitisch. <strong>Know-how wird immer wichtiger</strong>. Kluge Köpfe sind gefragt und\n\t\t\t\tfinden in diesem Bereich ein spannendes Umfeld mit vielfältigen Entwick­lungs­mög­lich­kei­ten für den\n\t\t\t\tberuflichen Lebensweg.<br>\n<br>\n\n<strong>Wagner, Elbling &amp; Company verfügt über dieses Know-how und sucht Sie zur Verstärkung</strong>\nunseres Teams! Seit mehr als 15 Jahren arbeiten wir mit führenden Vertretern der europäischen\nEnergieindustrie an der <strong>Mitgestaltung und Bewältigung dieses fundamentalen Wandels</strong>. Unser\nTätigkeitsbereich ist vielfältig. Er spannt den Bogen von Dekarbonisierungsstrategien für\nEnergieunternehmen auf allen Stufen der Wertschöpfungskette über Methoden im Energiehandel bis\nhin zur Weiterentwicklung der Regelwerke für die Energieliberalisierung in ganz Europa.<br>\n\n<strong>In diesen Bereichen sind wir einer der anerkanntesten Spieler der Branche.</strong><br>\n<br>\n\nZur Verstärkung unsers Teams suchen wir zum <strong>sofortigen Eintritt</strong> an unserem <strong>Haupt­sitz in der\nWiener Innenstadt</strong> neue Kolleginnen und Kollegen mit <strong>natur­wis­sens­chaft­lichem / technischem\nHintergrund</strong>, viel <strong>positiver Energie</strong> und <strong>Humor</strong>!\n\n<br>\n<br>\nDiese Anzeige richtet sich explizit auch an <strong>Berufseinsteiger</strong>. Wir wissen, dass aller Anfang schwer ist\nund deshalb unterstützen wir Sie in Ihrer Arbeit und beruflichen Entwicklung durch enge persönliche\nZusammenarbeit mit erfahrenen Kolleginnen und Kollegen in unseren Projektteams. \n<br><br>\nGemeinsam arbeiten Sie beispielsweise an folgenden Themen, wobei Schwerpunkte entsprechend Ihrer Ausbildung und Erfahrung gesetzt werden:\n\t\t    </p>\n            <ul type=\"disc\">\n\t\t\t\t<li> Ökonomische Analyse und quantitative Modellierung von Energiemärkten (Gas, Strom – Produktion, Speicherung, Netze, Verbrauch) vor dem Hintergrund mikroökonomischer, regulatorischer und wettbewerbsökonomischer Fragestellungen</li>\n\t\t\t\t<li> Berechnung der optimalen Ausgestaltung dekarbonisierter Energiesysteme für ganze Staaten unter Anwendung fortgeschrittener mathematischer Optimierungsverfahren</li>\n\t\t\t\t<li> Optimierung der Investitionsentscheidungen von Energieproduzenten (z.B. in Windparks, Biogasanlagen, etc.) vor dem Hintergrund von Dekarbonisierungsanforderungen, wirtschaftlichen Zielen und regulatorischen Rahmenbedingungen</li>\n\t\t\t\t<li> Entwicklung und Review von Regelwerken zur gezielten Weiterentwicklung von Energiemärkten</li>\n\t\t\t\t<li> (Prozess-)Modelle zur Abwicklung des Energietransports unter Beachtung der physikalisch / technischen Rahmenbedingungen der verfügbaren Netze</li>\n\t\t\t\t<li> Cyber-Security Konzepte für Betreiber kritischer Infrastrukturen</li>\n            </ul>\n            \n            \n            <p>Von erfolgreichen Bewerbern erwarten wir:</p>\n            <ul type=\"disc\">\n\t\t\t\t<li> mit sehr gutem Erfolg an einer Universität / TU abgeschlossenes naturwissenschaftliches / technisches Studium (Physik, Elektrotechnik, Energietechnik, Maschinenbau, Wirtschaftsingenieurwesen oder Vergleichbares)</li>\n\t\t\t\t<li> Bereitschaft, sich in die Details von Problemstellungen einzuarbeiten und Fähigkeit, dabei den Blick für den Gesamtzusammenhang zu wahren</li>\n\t\t\t\t<li> Freude an und ausgeprägte Fähigkeit zum quantitativen, datengetriebenen Arbeiten</li>\n\t\t\t\t<li> Interesse an erneuerbaren Energien und der Zukunft der Energieversorgung Österreichs und Europas</li>\n\t\t\t\t<li> Neugier und Bereitschaft, auch über den Bereich rein technischer / wirtschaftlicher Problemstellungen hinauszublicken und an deren Lösung mitzuwirken</li>\n\t\t\t\t<li> Freude an und Fähigkeit zur Teamarbeit</li>\n\t\t\t\t<li> sehr gute Kommunikationsfähigkeit in Wort und Schrift in deutscher und englischer Sprache</li>\n\t\t\t\t<li> Bereitschaft zu reisen (ca. 1-2 Arbeitstage pro Woche)</li>\n            </ul>\n            <p>\n\n\t\t\t\tIhre <strong>Karriere</strong> bei Wagner, Elbling &amp; Company ist ausschließlich durch Ihre Leistung bestimmt und führt über die anfängliche Mitarbeit in Projektteams bis hin zum er­geb­nis­ver­antwortlichen Projektleiter. Auf allen Stufen der Karriereleiter bieten wir ein <strong>weit überdurchschnittliches Gehalt</strong> und das bei einem Arbeitsumfang, der auch noch <strong>Zeit zum Leben</strong> lässt.<br>\n<br>\n\nBitte senden Sie Ihre <strong>aussagekräftigen Unterlagen</strong> (Lebenslauf mit Farbfoto, Univer­si­täts­zeu­gnisse, Maturazeugnis, ggf. Arbeitszeugnisse) mit Angabe des frü­hest­mög­lichen Eintrittstermins an: <a><span data-mux=\"tooltip\" data-placement=\"top\" title=\"\" class=\"mux-tooltip\" mux1590466089470=\"1\" data-original-title=\"Bitte nutze für eine Bewerbung den Bewerben-Button. Falls dieser nicht vorhanden sein sollte, nutze bitte die Kontaktinformation in der Stellenanzeige.\">recruiting@wecom.at</span></a>. Auch Rückfragen können gerne an diese Adresse gerichtet werden.\n<br>\n<br>\n\n<strong>Wir freuen uns auf Sie – freuen Sie sich auf uns!</strong>\n\t\t    </p>\n          </div>\n          <br>\n          <img alt=\"\" src=\"https://media.newjobs.com/ftpinta/xjp66326atx/xjp66326atx_e005.gif\" width=\"471\" height=\"1\"></td>\n        <td background=\"https://media.newjobs.com/ftpinta/xjp66326atx/xjp66326atx_e002.gif\"><img alt=\"\" src=\"https://media.newjobs.com/ftpinta/xjp66326atx/xjp66326atx_e002.gif\" class=\"noprint\" width=\"64\" height=\"1\"></td>\n      </tr>\n      <tr>\n        <td><img alt=\"\" src=\"https://media.newjobs.com/ftpinta/xjp66326atx/xjp66326atx_e006.gif\" class=\"noprint\" width=\"65\" height=\"20\"></td>\n        <td><img alt=\"\" src=\"https://media.newjobs.com/ftpinta/xjp66326atx/xjp66326atx_e007.gif\" class=\"noprint\" width=\"471\" height=\"20\"></td>\n        <td><img alt=\"\" src=\"https://media.newjobs.com/ftpinta/xjp66326atx/xjp66326atx_e008.gif\" class=\"noprint\" width=\"64\" height=\"20\"></td>\n      </tr>\n      <tr>\n        <td background=\"https://media.newjobs.com/ftpinta/xjp66326atx/xjp66326atx_e004.gif\"><img alt=\"\" src=\"https://media.newjobs.com/ftpinta/xjp66326atx/xjp66326atx_e004.gif\" class=\"noprint\" width=\"65\" height=\"1\"></td>\n        <td background=\"https://media.newjobs.com/ftpinta/xjp66326atx/xjp66326atx_e005.gif\"><br>\n          <div class=\"text1\"><b>Kontakt:</b></div>\n          <table width=\"100%\" cellspacing=\"0\" cellpadding=\"0\" border=\"0\">\n            <tbody>\n              <tr>\n                <td width=\"50%\"><div class=\"text\"><b>Wagner, Elbling &amp; Company</b><br>\n                    Management Advisors<br>\n                    <a data-role=\"none\"><span data-mux=\"tooltip\" data-placement=\"top\" title=\"\" class=\"mux-tooltip\" mux1590466089470=\"2\" data-original-title=\"Bitte nutze für eine Bewerbung den Bewerben-Button. Falls dieser nicht vorhanden sein sollte, nutze bitte die Kontaktinformation in der Stellenanzeige.\">recruiting@wecom.at</span></a><br>\n                    <a data-role=\"none\" href=\"http://www.wecom.at\" target=\"_blank\">www.wecom.at</a> </div></td>\n                <td width=\"50%\"><div class=\"ref\">Geschäftsführer:\n                    Dr. Albrecht Wagner <br>\n                    Mag. Oliver Elbling<br>\n                    Seilerstätte 18-20/3.OG, 1010 Wien<br>\n                  </div></td>\n              </tr>\n            </tbody>\n          </table>\n          <img alt=\"\" src=\"https://media.newjobs.com/ftpinta/xjp66326atx/xjp66326atx_e005.gif\" width=\"471\" height=\"1\"></td>\n        <td background=\"https://media.newjobs.com/ftpinta/xjp66326atx/xjp66326atx_e002.gif\"><img alt=\"\" src=\"https://media.newjobs.com/ftpinta/xjp66326atx/xjp66326atx_e002.gif\" class=\"noprint\" width=\"64\" height=\"1\"></td>\n      </tr>\n      <tr>\n        <td><img alt=\"\" src=\"https://media.newjobs.com/ftpinta/xjp66326atx/xjp66326atx_e009.gif\" class=\"noprint\" width=\"65\" height=\"25\"></td>\n        <td><img alt=\"\" src=\"https://media.newjobs.com/ftpinta/xjp66326atx/xjp66326atx_e010.gif\" class=\"noprint\" width=\"471\" height=\"25\"></td>\n        <td><img alt=\"\" src=\"https://media.newjobs.com/ftpinta/xjp66326atx/xjp66326atx_e011.gif\" class=\"noprint\" width=\"64\" height=\"25\"></td>\n      </tr>\n    </tbody>\n  </table>\n</center>\n</span>\n<i_jt_footer visible=\"True\" expressapply=\"True\"></i_jt_footer>\n\n\n",
  "url": "https://stellenangebot.monster.at/naturwissenschaftler-in-techniker-in-energiewirtschaft-jahresgehalt-ab-%E2%82%AC-60-000-wien-w-at-wagner-elbling-company/213126715",
  "date": "2020-05-26"
}